<?xml version="1.0" encoding="utf-8"?>
<!DOCTYPE hibernate-mapping PUBLIC "-//Hibernate/Hibernate Mapping DTD 3.0//EN"
"http://hibernate.sourceforge.net/hibernate-mapping-3.0.dtd">
<!-- 
    Mapping file autogenerated by MyEclipse Persistence Tools
-->
<hibernate-mapping>
    <class name="com.serviceDesk.common.domain.TDcDatacenterbaseinfo" table="T_DC_DATACENTERBASEINFO" schema="SCOTT">
        <id name="FDatacenterid" type="java.lang.String">
            <column name="F_DATACENTERID" length="6" />
            <generator class="sequence" />
        </id>
        <property name="FDatacentername" type="java.lang.String">
            <column name="F_DATACENTERNAME" length="48" not-null="true" />
        </property>
        <property name="FDatacentertype" type="java.math.BigDecimal">
            <column name="F_DATACENTERTYPE" precision="22" scale="0" not-null="true" />
        </property>
        <property name="FDatacentermanager" type="java.math.BigDecimal">
            <column name="F_DATACENTERMANAGER" precision="22" scale="0" />
        </property>
        <property name="FDatacenterdesc" type="java.lang.String">
            <column name="F_DATACENTERDESC" length="48" />
        </property>
        <property name="FDatacentercontact" type="java.lang.String">
            <column name="F_DATACENTERCONTACT" length="48" />
        </property>
        <property name="FDatacentertel" type="java.lang.String">
            <column name="F_DATACENTERTEL" length="48" />
        </property>
        <set name="TMoOrgbaseinfos" inverse="true">
            <key>
                <column name="F_DATACENTERID" length="6" />
            </key>
            <one-to-many class="com.serviceDesk.common.domain.TMoOrgbaseinfo" />
        </set>
        <set name="TBdBuildbaseinfos" inverse="true">
            <key>
                <column name="F_DATACENTERID" length="6" />
            </key>
            <one-to-many class="com.serviceDesk.common.domain.TBdBuildbaseinfo" />
        </set>
    </class>
</hibernate-mapping>
